codechecklib/__init__.py
codechecklib/const.py
codechecklib/example_code.py
codechecklib/sandbox.py
codechecklib/tester.py
codechecklib-0.3.15.1.dist-info/METADATA
codechecklib-0.3.15.1.dist-info/WHEEL
codechecklib-0.3.15.1.dist-info/top_level.txt
codechecklib-0.3.15.1.dist-info/RECORD
