Metadata-Version: 2.1
Name: codechecklib
Version: 0.3.15.1
Summary: Simple sandbox & testing utility
Home-page: https://hub.vanutp.dev
Author: vanutp
Author-email: hello@vanutp.dev
License: UNKNOWN
Platform: UNKNOWN
Requires-Python: >=3.8
